nonebot_plugin_myb_exchange/__init__.py
nonebot_plugin_myb_exchange/data_source.py
nonebot_plugin_myb_exchange/utils.py
nonebot_plugin_myb_exchange-1.0.0.dist-info/WHEEL
nonebot_plugin_myb_exchange-1.0.0.dist-info/METADATA
nonebot_plugin_myb_exchange-1.0.0.dist-info/RECORD
