Metadata-Version: 2.1
Name: nonebot-plugin-myb-exchange
Version: 1.0.0
Summary: Nonebot2米游币商品自动兑换插件
Home-page: https://github.com/CMHopeSunshine/LittlePaimon/tree/Bot/src/plugins/nonebot_plugin_myb_exchange
License: AGPL
Keywords: nonebot,nonebot2,mihoyo
Author: 惜月
Author-email: 277073121@qq.com
Requires-Python: >=3.7.3,<4.0.0
Classifier: License :: Other/Proprietary License
Classifier: Programming Language :: Python :: 3
Classifier: Programming Language :: Python :: 3.10
Classifier: Programming Language :: Python :: 3.8
Classifier: Programming Language :: Python :: 3.9
Requires-Dist: httpx (>=0.23.0,<0.24.0)
Requires-Dist: nonebot-adapter-onebot (>=2.0.0-beta.1,<3.0.0)
Requires-Dist: nonebot-plugin-apscheduler (>=0.1.2,<0.2.0)
Requires-Dist: nonebot2 (>=2.0.0-beta.4,<3.0.0)
Project-URL: Documentation, https://github.com/CMHopeSunshine/LittlePaimon/tree/Bot/src/plugins/nonebot_plugin_myb_exchange#readme
Project-URL: Repository, https://github.com/CMHopeSunshine/LittlePaimon/tree/Bot/src/plugins/nonebot_plugin_myb_exchange
